{"name": [{"word": "\u043f\u043e\u0434\u044b\u0441\u043a\u0430\u0432\u0448\u0435\u044e", "bbox": [[202, 215], [344, 215], [344, 229], [202, 229]], "font_name": "Alice-Regular.ttf", "font_size": 23, "color": "#c0a254"}, {"word": "\u0447\u0438\u0440\u043a\u0430\u043b", "bbox": [[391, 219], [393, 170], [562, 176], [560, 225]], "font_name": "Alice-Regular.ttf", "font_size": 52, "color": "#5eba79"}, {"word": "\u0431\u0443\u0442\u0443\u0437\u0435", "bbox": [[170, 418], [209, 416], [210, 425], [171, 427]], "font_name": "Alice-Regular.ttf", "font_size": 16, "color": "#2a5338"}, {"word": "\u0434\u043e\u0436\u0434\u0435\u043f\u0440\u0438\u0435\u043c\u043d\u0438\u043a\u0430\u043c", "bbox": [[26, 262], [27, 247], [223, 260], [222, 276]], "font_name": "Alice-Regular.ttf", "font_size": 23, "color": "#6e834a"}, {"word": "\u0437\u0430\u0431\u044b\u043b\u043e\u0441\u044c", "bbox": [[172, 108], [175, 64], [422, 81], [419, 125]], "font_name": "Alice-Regular.ttf", "font_size": 58, "color": "#04b52d"}, {"word": "\u0444\u0440\u0430\u043a\u0446\u0438\u0435\u044e", "bbox": [[164, 315], [345, 311], [346, 345], [165, 348]], "font_name": "Alice-Regular.ttf", "font_size": 39, "color": "#faf673"}, {"word": "\u0442\u043e\u043a\u0441\u0438\u043a\u043e\u043b\u043e\u0433\u0438\u044e", "bbox": [[248, 173], [346, 166], [347, 171], [249, 178]], "font_name": "Alice-Regular.ttf", "font_size": 16, "color": "#5e5bf2"}, {"word": "\u043a\u0435\u0441\u0430\u0440\u0435\u0432\u044b\u043c", "bbox": [[425, 120], [512, 120], [512, 131], [425, 131]], "font_name": "Alice-Regular.ttf", "font_size": 19, "color": "#e67fad"}, {"word": "\u0432\u044b\u0434\u0432\u043e\u0440\u0438\u0432\u0448\u0435\u0435", "bbox": [[265, 441], [269, 391], [603, 420], [599, 470]], "font_name": "Alice-Regular.ttf", "font_size": 53, "color": "#6b3800"}, {"word": "\u0443\u043f\u0440\u043e\u0449\u0435\u043d\u0438\u0435\u043c", "bbox": [[327, 385], [328, 369], [457, 373], [456, 389]], "font_name": "Alice-Regular.ttf", "font_size": 23, "color": "#f29f62"}, {"word": "\u0441\u043c\u0440\u0430\u0434\u043d\u044b\u0439", "bbox": [[419, 233], [552, 226], [554, 250], [420, 257]], "font_name": "Alice-Regular.ttf", "font_size": 30, "color": "#d9d29f"}, {"word": "\u0434\u0438\u043a\u0442\u0443\u0435\u043c\u0430\u044f", "bbox": [[390, 273], [624, 265], [626, 309], [392, 317]], "font_name": "Alice-Regular.ttf", "font_size": 48, "color": "#0eb455"}, {"word": "\u0441\u0442\u043e\u0440\u043d\u0438\u0440\u043e\u0432\u0430\u0442\u044c\u0441\u044f", "bbox": [[38, 91], [39, 85], [134, 92], [133, 98]], "font_name": "Alice-Regular.ttf", "font_size": 14, "color": "#9554ee"}, {"word": "\u0436\u0435\u0440\u0451\u0431\u043e\u0435", "bbox": [[258, 15], [315, 15], [315, 25], [258, 25]], "font_name": "Alice-Regular.ttf", "font_size": 17, "color": "#18921f"}, {"word": "\u0437\u0430\u0434\u0451\u0440\u043d\u0443\u043b\u0438\u0441\u044c", "bbox": [[217, 287], [301, 281], [302, 290], [218, 296]], "font_name": "Alice-Regular.ttf", "font_size": 16, "color": "#a85f63"}, {"word": "\u043c\u043e\u043b\u0435\u043b\u044c\u0449\u0438\u0446\u0435\u0439", "bbox": [[137, 408], [138, 401], [228, 404], [227, 411]], "font_name": "Alice-Regular.ttf", "font_size": 15, "color": "#a27a95"}, {"word": "\u0443\u0442\u044f\u0436\u0435\u043b\u044f\u0432\u0448\u0435\u0435", "bbox": [[162, 50], [163, 40], [264, 44], [263, 54]], "font_name": "Alice-Regular.ttf", "font_size": 17, "color": "#706ac1"}, {"word": "\u043e\u0442\u0442\u0430\u0441\u043a\u0430\u043d\u043d\u044b\u0435", "bbox": [[514, 157], [630, 153], [631, 163], [515, 167]], "font_name": "Alice-Regular.ttf", "font_size": 21, "color": "#c19573"}, {"word": "\u043c\u0443\u0434\u0440\u0451\u043d\u043e\u0441\u0442\u0438", "bbox": [[149, 354], [229, 354], [229, 362], [149, 362]], "font_name": "Alice-Regular.ttf", "font_size": 16, "color": "#e74003"}, {"word": "\u043a\u043e\u043b\u044f\u0441\u043a\u043e\u0439", "bbox": [[533, 94], [534, 85], [613, 87], [612, 96]], "font_name": "Alice-Regular.ttf", "font_size": 20, "color": "#bae866"}, {"word": "\u043e\u0442\u043f\u0438\u0432\u0430\u044f", "bbox": [[475, 393], [476, 383], [552, 388], [551, 398]], "font_name": "Alice-Regular.ttf", "font_size": 22, "color": "#bddb9f"}, {"word": "\u043f\u043e\u043a\u0440\u044b\u0442\u044c", "bbox": [[446, 69], [447, 60], [501, 63], [500, 72]], "font_name": "Alice-Regular.ttf", "font_size": 16, "color": "#c88053"}, {"word": "\u0438\u0437\u0436\u0430\u0440\u044c\u0442\u0435\u0441\u044c", "bbox": [[341, 30], [441, 23], [442, 36], [342, 43]], "font_name": "Alice-Regular.ttf", "font_size": 20, "color": "#1e140e"}, {"word": "\u0441\u043e\u043d\u0430\u0440\u0435", "bbox": [[494, 135], [538, 135], [538, 144], [494, 144]], "font_name": "Alice-Regular.ttf", "font_size": 17, "color": "#ffbb24"}, {"word": "\u043f\u0440\u0438\u0449\u0435\u043f\u043b\u044f\u044f\u0441\u044c", "bbox": [[382, 347], [561, 338], [563, 361], [383, 370]], "font_name": "Alice-Regular.ttf", "font_size": 29, "color": "#7a8ac5"}, {"word": "\u043d\u0430\u043c\u0451\u0442\u043e\u043a", "bbox": [[459, 49], [529, 44], [530, 53], [460, 58]], "font_name": "Alice-Regular.ttf", "font_size": 20, "color": "#cd7709"}, {"word": "\u0432\u0435\u0441\u044c\u044e", "bbox": [[122, 413], [162, 411], [163, 418], [123, 420]], "font_name": "Alice-Regular.ttf", "font_size": 18, "color": "#d04b1d"}, {"word": "\u043f\u0440\u043e\u0437\u044b\u0432\u0430\u044e\u0449\u0438\u0445\u0441\u044f", "bbox": [[34, 193], [133, 191], [134, 197], [35, 199]], "font_name": "Alice-Regular.ttf", "font_size": 14, "color": "#17faf2"}, {"word": "\u0442\u0440\u0435\u043d\u0438\u0440\u043e\u0432\u043e\u043a", "bbox": [[275, 200], [370, 197], [371, 209], [276, 212]], "font_name": "Alice-Regular.ttf", "font_size": 19, "color": "#a384f4"}, {"word": "\u043e\u0431\u0447\u0438\u0441\u0442\u0438\u0442", "bbox": [[70, 171], [71, 159], [165, 161], [164, 173]], "font_name": "Alice-Regular.ttf", "font_size": 24, "color": "#b61094"}, {"word": "\u0441\u043e\u0440\u0435\u0432\u043d\u043e\u0432\u0430\u0432\u0448\u0435\u0433\u043e\u0441\u044f", "bbox": [[26, 241], [28, 225], [219, 242], [217, 258]], "font_name": "Alice-Regular.ttf", "font_size": 23, "color": "#363ef8"}, {"word": "\u0441\u0443\u0431\u0441\u0438\u0434\u0438\u0440\u043e\u0432\u0430\u043b", "bbox": [[62, 435], [224, 426], [225, 445], [63, 454]], "font_name": "Alice-Regular.ttf", "font_size": 26, "color": "#2c95c0"}, {"word": "\u043f\u044f\u0442\u0451\u0440\u043e\u043a", "bbox": [[185, 137], [234, 135], [234, 141], [186, 144]], "font_name": "Alice-Regular.ttf", "font_size": 15, "color": "#d4dc04"}, {"word": "\u043f\u043e\u043b\u0437\u0443\u0447\u0435", "bbox": [[26, 289], [80, 289], [80, 299], [26, 299]], "font_name": "Alice-Regular.ttf", "font_size": 17, "color": "#6f8c0f"}, {"word": "\u0445\u043d\u044b\u043a\u0430\u0432\u0448\u0430\u044f", "bbox": [[518, 80], [519, 73], [607, 75], [606, 82]], "font_name": "Alice-Regular.ttf", "font_size": 18, "color": "#43012e"}, {"word": "\u0442\u043e\u043a\u043e\u0432", "bbox": [[89, 343], [142, 343], [142, 355], [89, 355]], "font_name": "Alice-Regular.ttf", "font_size": 24, "color": "#0d53f4"}, {"word": "\u043f\u043b\u0430\u043d\u0435\u0442\u043a\u0443", "bbox": [[287, 154], [288, 138], [380, 140], [379, 156]], "font_name": "Alice-Regular.ttf", "font_size": 23, "color": "#0ed908"}, {"word": "\u0432\u044b\u0441\u0442\u0440\u043e\u044e", "bbox": [[372, 58], [373, 51], [425, 53], [424, 60]], "font_name": "Alice-Regular.ttf", "font_size": 15, "color": "#386d83"}, {"word": "\u043f\u0430\u0444\u043d\u0443\u0442\u044c\u0435\u0432\u043d\u0435", "bbox": [[39, 332], [40, 320], [146, 324], [145, 336]], "font_name": "Alice-Regular.ttf", "font_size": 19, "color": "#e7a974"}, {"word": "\u043f\u043e\u0433\u043e\u043d\u044b\u0448\u0430", "bbox": [[66, 151], [142, 147], [143, 154], [67, 158]], "font_name": "Alice-Regular.ttf", "font_size": 18, "color": "#4688c5"}, {"word": "\u043f\u0435\u0440\u0435\u0432\u0435\u0434\u0448\u0435\u0433\u043e\u0441\u044f", "bbox": [[231, 244], [386, 236], [387, 252], [232, 260]], "font_name": "Alice-Regular.ttf", "font_size": 23, "color": "#4a63b8"}, {"word": "\u0440\u0430\u0437\u0443\u0447\u0438\u0432\u0430\u0432\u0448\u0435\u0433\u043e", "bbox": [[28, 42], [132, 40], [133, 49], [29, 51]], "font_name": "Alice-Regular.ttf", "font_size": 16, "color": "#94c124"}, {"word": "\u043e\u0431\u043e\u043b\u0433\u0430\u043d\u043d\u044b\u043c\u0438", "bbox": [[487, 116], [488, 110], [587, 119], [586, 125]], "font_name": "Alice-Regular.ttf", "font_size": 17, "color": "#748406"}, {"word": "\u043a\u043d\u044f\u0437\u0438\u0448\u043a\u0430", "bbox": [[196, 393], [262, 389], [263, 394], [197, 397]], "font_name": "Alice-Regular.ttf", "font_size": 16, "color": "#a4acf8"}, {"word": "\u043e\u043f\u0435\u043a\u0430\u0435\u043c\u044b\u0439", "bbox": [[33, 106], [34, 100], [113, 104], [112, 110]], "font_name": "Alice-Regular.ttf", "font_size": 17, "color": "#2f76e4"}, {"word": "\u0436\u043c\u0443\u0440\u0438\u0432\u0448\u0443\u044e", "bbox": [[431, 323], [511, 318], [512, 325], [432, 330]], "font_name": "Alice-Regular.ttf", "font_size": 15, "color": "#958002"}]}